labyrinthine/__init__.py
labyrinthine/depth_first.py
labyrinthine-0.1.11.dist-info/LICENSE
labyrinthine-0.1.11.dist-info/METADATA
labyrinthine-0.1.11.dist-info/WHEEL
labyrinthine-0.1.11.dist-info/top_level.txt
labyrinthine-0.1.11.dist-info/zip-safe
labyrinthine-0.1.11.dist-info/RECORD
