Metadata-Version: 2.1
Name: labyrinthine
Version: 0.1.11
Summary: A no-dependency library to generate mazes.
Author-email: Roberto Schiavone <hello@robertoschiavone.io>
Maintainer-email: Roberto Schiavone <hello@robertoschiavone.io>
License: MIT License
Project-URL: homepage, https://github.com/robertoschiavone/labyrinthine
Project-URL: documentation, https://github.com/robertoschiavone/labyrinthine
Project-URL: repository, https://github.com/robertoschiavone/labyrinthine.git
Project-URL: changelog, https://github.com/robertoschiavone/labyrinthine/releases
Keywords: maze,procedural-generation
Classifier: License :: OSI Approved :: MIT License
Classifier: Programming Language :: Python :: 3
Classifier: Topic :: Software Development :: Libraries
Requires-Python: >=3.5
License-File: LICENSE
